mcp_server_trino/__init__.py
mcp_server_trino/server.py
iflow_mcp_mcp_server_trino-0.1.1.dist-info/METADATA
iflow_mcp_mcp_server_trino-0.1.1.dist-info/WHEEL
iflow_mcp_mcp_server_trino-0.1.1.dist-info/entry_points.txt
iflow_mcp_mcp_server_trino-0.1.1.dist-info/licenses/LICENSE
iflow_mcp_mcp_server_trino-0.1.1.dist-info/RECORD
