Metadata-Version: 2.4
Name: iflow-mcp_mcp_server_trino
Version: 0.1.1
Summary: A Model Context Protocol (MCP) server that enables secure interaction with Trino. This server allows AI assistants to list tables, read data, and execute SQL queries through a controlled interface, making data exploration and analysis safer and more structured.
Author-email: Mahesh Premachandran <mahesh@getdataring.com>
License-File: LICENSE
Requires-Python: >=3.11
Requires-Dist: mcp>=1.0.0
Requires-Dist: trino==0.333.0
